waka_relay-0.2.0.dist-info/licenses/LICENSE
wakarelay/__init__.py
wakarelay/main.py
waka_relay-0.2.0.dist-info/METADATA
waka_relay-0.2.0.dist-info/WHEEL
waka_relay-0.2.0.dist-info/entry_points.txt
waka_relay-0.2.0.dist-info/top_level.txt
waka_relay-0.2.0.dist-info/RECORD
