Metadata-Version: 2.4
Name: waka-relay
Version: 0.2.0
Summary: A self-hosted app that relays WakaTime heartbeats to multiple instances.
Author: ShyMike
License: AGPL-3.0
Project-URL: Source, https://github.com/ImShyMike/waka-relay
Classifier: Environment :: Console
Classifier: Programming Language :: Python
Requires-Python: >=3.8
License-File: LICENSE
Requires-Dist: fastapi[standard]
Requires-Dist: toml
Requires-Dist: uvicorn
Requires-Dist: uvicorn-worker
Requires-Dist: httpx
Dynamic: license-file
